jsonmapping/__init__.py
jsonmapping/elastic.py
jsonmapping/mapper.py
jsonmapping/network.py
jsonmapping/statements.py
jsonmapping/transforms.py
jsonmapping/util.py
jsonmapping/value.py
jsonmapping/visitor.py
jsonmapping/schemas/mapping.json
jsonmapping-0.7.4.dist-info/DESCRIPTION.rst
jsonmapping-0.7.4.dist-info/METADATA
jsonmapping-0.7.4.dist-info/RECORD
jsonmapping-0.7.4.dist-info/WHEEL
jsonmapping-0.7.4.dist-info/metadata.json
jsonmapping-0.7.4.dist-info/namespace_packages.txt
jsonmapping-0.7.4.dist-info/top_level.txt
tests/__init__.py
tests/test_mapping.py
tests/test_network.py
tests/test_statements.py
tests/util.py
