Metadata-Version: 2.0
Name: jsonmapping
Version: 0.7.4
Summary: Map flat data to structured JSON via a mapping.
Home-page: http://github.com/pudo/jsonmapping
Author: Friedrich Lindenberg
Author-email: friedrich@pudo.org
License: MIT
Keywords: schema jsonschema json data conversion
Platform: UNKNOWN
Classifier: Development Status :: 3 - Alpha
Classifier: Intended Audience :: Developers
Classifier: License :: OSI Approved :: MIT License
Classifier: Operating System :: OS Independent
Classifier: Programming Language :: Python :: 2.6
Classifier: Programming Language :: Python :: 2.7
Classifier: Programming Language :: Python :: 3.3
Classifier: Programming Language :: Python :: 3.4
Requires-Dist: jsonschema
Requires-Dist: networkx
Requires-Dist: normality
Requires-Dist: six
Requires-Dist: typecast
Requires-Dist: unidecode
